winlog.py
WinLog-0.0.1.dist-info/LICENSE
WinLog-0.0.1.dist-info/METADATA
WinLog-0.0.1.dist-info/WHEEL
WinLog-0.0.1.dist-info/entry_points.txt
WinLog-0.0.1.dist-info/top_level.txt
WinLog-0.0.1.dist-info/RECORD
