Metadata-Version: 2.1
Name: WinLog
Version: 0.0.1
Summary: A Python script to log active Windows title to desktop log
Home-page: https://github.com/sukhbinder/winlog
Author: Sukhbinder Singh
Author-email: sukh2010@yahoo.com
License: Apache License, Version 2.0
Project-URL: Documentation, https://sukhbinder.wordpress.com
Project-URL: Issues, https://github.com/sukhbinder/winlog/issues
Project-URL: CI, https://github.com/sukhbinder/winlog/actions
Project-URL: Changelog, https://github.com/sukhbinder/winlog/releases
Requires-Python: >=3.8
License-File: LICENSE
Provides-Extra: test
Requires-Dist: pytest ; extra == 'test'
